[{"id":"1","apartment":{"id":"1","flag":0},"startDateOfReservation":1597765860000,"numberOfNights":3,"fullPrice":150.0,"reservationMessage":"CAO","guest":{"username":"nemanja","flag":0},"statusOfReservation":"ACCEPTED","flag":0},{"id":"2","apartment":{"id":"1","flag":0},"startDateOfReservation":1598371080000,"numberOfNights":3,"fullPrice":150.0,"reservationMessage":"CAO CAO","guest":{"username":"nemanja","flag":0},"statusOfReservation":"CREATED","flag":0},{"id":"3","apartment":{"id":"2","flag":0},"startDateOfReservation":1597853400000,"numberOfNights":2,"fullPrice":120.0,"reservationMessage":"eeeej","guest":{"username":"nemanja","flag":0},"statusOfReservation":"CREATED","flag":0}]